wink_sdk_extranet_facilities/__init__.py
wink_sdk_extranet_facilities/api_client.py
wink_sdk_extranet_facilities/api_response.py
wink_sdk_extranet_facilities/configuration.py
wink_sdk_extranet_facilities/exceptions.py
wink_sdk_extranet_facilities/py.typed
wink_sdk_extranet_facilities/rest.py
wink_sdk_extranet_facilities/api/__init__.py
wink_sdk_extranet_facilities/api/guest_room_api.py
wink_sdk_extranet_facilities/api/meeting_room_api.py
wink_sdk_extranet_facilities/api/restaurant_api.py
wink_sdk_extranet_facilities/api/spa_api.py
wink_sdk_extranet_facilities/models/__init__.py
wink_sdk_extranet_facilities/models/address.py
wink_sdk_extranet_facilities/models/address_supplier.py
wink_sdk_extranet_facilities/models/bed.py
wink_sdk_extranet_facilities/models/bed_supplier.py
wink_sdk_extranet_facilities/models/bedroom.py
wink_sdk_extranet_facilities/models/bedroom_configuration.py
wink_sdk_extranet_facilities/models/bedroom_configuration_supplier.py
wink_sdk_extranet_facilities/models/bedroom_supplier.py
wink_sdk_extranet_facilities/models/contact.py
wink_sdk_extranet_facilities/models/contact_supplier.py
wink_sdk_extranet_facilities/models/country.py
wink_sdk_extranet_facilities/models/country_lightweight.py
wink_sdk_extranet_facilities/models/country_lightweight_supplier.py
wink_sdk_extranet_facilities/models/country_supplier.py
wink_sdk_extranet_facilities/models/custom_monetary_amount.py
wink_sdk_extranet_facilities/models/dow_pattern_group_supplier.py
wink_sdk_extranet_facilities/models/duplicate_guest_room_request_supplier.py
wink_sdk_extranet_facilities/models/generic_error_message.py
wink_sdk_extranet_facilities/models/geo_json_point.py
wink_sdk_extranet_facilities/models/geo_json_point_supplier.py
wink_sdk_extranet_facilities/models/geo_name.py
wink_sdk_extranet_facilities/models/geo_name_lightweight.py
wink_sdk_extranet_facilities/models/geo_name_lightweight_supplier.py
wink_sdk_extranet_facilities/models/geo_name_supplier.py
wink_sdk_extranet_facilities-0.0.57.dist-info/licenses/LICENSE
wink_sdk_extranet_facilities-0.0.57.dist-info/METADATA
wink_sdk_extranet_facilities-0.0.57.dist-info/WHEEL
wink_sdk_extranet_facilities-0.0.57.dist-info/top_level.txt
wink_sdk_extranet_facilities-0.0.57.dist-info/RECORD
